aiopinboard/__init__.py
aiopinboard/api.py
aiopinboard/bookmark.py
aiopinboard/errors.py
aiopinboard/helpers/types.py
aiopinboard/note.py
aiopinboard/py.typed
aiopinboard/tag.py
aiopinboard-2024.1.0.dist-info/LICENSE
aiopinboard-2024.1.0.dist-info/METADATA
aiopinboard-2024.1.0.dist-info/WHEEL
aiopinboard-2024.1.0.dist-info/RECORD
