Metadata-Version: 2.1
Name: aiopinboard
Version: 2024.1.0
Summary: A Python 3, asyncio-based library for the Pinboard API
Home-page: https://github.com/bachya/aiopinboard
License: MIT
Author: Aaron Bach
Author-email: bachya1208@gmail.com
Requires-Python: >=3.10,<4.0
Classifier: License :: OSI Approved :: MIT License
Classifier: Programming Language :: Python
Classifier: Programming Language :: Python :: 3
Classifier: Programming Language :: Python :: 3.10
Classifier: Programming Language :: Python :: 3.11
Classifier: Programming Language :: Python :: 3.12
Classifier: Programming Language :: Python :: Implementation :: CPython
Classifier: Programming Language :: Python :: Implementation :: PyPy
Classifier: Typing :: Typed
Requires-Dist: aiohttp (>=3.8.0)
Requires-Dist: arrow (>=1.3.0,<2.0.0)
Requires-Dist: certifi (>=2023.07.22)
Requires-Dist: frozenlist (>=1.4.0,<2.0.0)
Requires-Dist: yarl (>=1.9.2)
Project-URL: Bug Tracker, https://github.com/bachya/aiopinboard/issues
Project-URL: Changelog, https://github.com/bachya/aiopinboard/releases
Project-URL: Repository, https://github.com/bachya/aiopinboard
